{
  "black": {
    "base": {
      "hex": "#000000",
      "map": "primary"
    }
  },
  "white": {
    "base": {
      "hex": "#ffffff",
      "map": "secondary"
    }
  },
  "cyan": {
    "light":  {"hex": "#a2ffff"},
    "base": {"hex": "#00ffff"},
    "dark":   {"hex": "#00e5e5"}
  },
  "yellow": {
    "light":  {"hex": "#fff9a3"},
    "base": {"hex": "#fff44f"},
    "dark":   {"hex": "#f7e800"}
  },
  "red": {
    "light":  {"hex": "#fe7c87"},
    "base": {"hex": "#ff4f5e"},
    "dark":   {"hex": "#e53c4a"}
  },
  "green": {
    "light":  {"hex": "#adffdf"},
    "base": {"hex": "#54ffbd"},
    "dark":   {"hex": "#2ce69e"}
  },
  "teal": {
    "light":  {"hex": "#25bcbc"},
    "base": {"hex": "#0f8f8f"},
    "dark":   {"hex": "#005e5e"}
  },
  "purple": {
    "light":  {"hex": "#9f54b2"},
    "base": {"hex": "#6e008b"},
    "dark":   {"hex": "#4f0164"}
  },
  "blue": {
    "light":  {
      "hex": "#539ee9",
      "map": "link-hover"
    },
    "base": {
      "hex": "#2374c6",
      "map": "link"
    },
    "dark":   {
      "hex": "#00458b",
      "map": "link-active"
    }
  },
  "gray": {
    "light":  {"hex": "#e7e7e7"},
    "base": {"hex": "#c8c8c8"},
    "dark":   {"hex": "#959595"}
  }
}
